meteo_utils/__init__.py
meteo_utils/dem_utils.py
meteo_utils/ecmwf_utils.py
meteo_utils/gdal_utils.py
meteo_utils/solar_irradiance.py
meteo_utils-2.1.0.dist-info/licenses/LICENSE
meteo_utils-2.1.0.dist-info/METADATA
meteo_utils-2.1.0.dist-info/WHEEL
meteo_utils-2.1.0.dist-info/top_level.txt
meteo_utils-2.1.0.dist-info/RECORD
