Metadata-Version: 2.4
Name: meteo_utils
Version: 2.1.0
Summary: Python methods for the automatic download and processing of ECMWF data relevant for evapotranspiration modelling.
Author-email: Héctor Nieto <hector.nieto@csic.es>, Radoslaw Guzinski <rmgu@dhigroup.com>
License-Expression: GPL-3.0-or-later
Project-URL: Homepage, https://github.com/hectornieto/meteo_utils
Keywords: SEN-ET,Evapotranspiration,Landsat,Sentinel-3,SLSTR,Copernicus,ERA5,CAMS,ECMWF,Remote Sensing
Classifier: Development Status :: 5 - Production/Stable
Classifier: Intended Audience :: Science/Research
Classifier: Topic :: Scientific/Engineering :: Hydrology
Classifier: Topic :: Software Development :: Libraries :: Python Modules
Classifier: Programming Language :: Python
Classifier: Programming Language :: Python :: 3
Requires-Python: >=3.6
License-File: LICENSE
Requires-Dist: cdsapi
Requires-Dist: netCDF4
Requires-Dist: numpy
Requires-Dist: gdal
Requires-Dist: osr
Requires-Dist: scipy
Requires-Dist: scikit-image
Requires-Dist: pyyaml
Requires-Dist: cfgrib
Requires-Dist: xarray
Requires-Dist: rioxarray
Requires-Dist: radiative-transfer-models
Requires-Dist: pytseb
Requires-Dist: python-dms
Dynamic: license-file
